trailbase/__init__.py
trailbase-0.4.0.dist-info/METADATA
trailbase-0.4.0.dist-info/WHEEL
trailbase-0.4.0.dist-info/RECORD
